{
  "project_info": {
    "project_number": "237115759240",
    "firebase_url": "https://dietapp-in-default-rtdb.asia-southeast1.firebasedatabase.app",
    "project_id": "dietapp-in",
    "storage_bucket": "dietapp-in.appspot.com"
  },
  "client": [
    {
      "client_info": {
        "mobilesdk_app_id": "1:237115759240:android:9c2e9df328f6c01bfc9d3d",
        "android_client_info": {
          "package_name": "com.example.dietapp_v001"
        }
      },
      "oauth_client": [
        {
          "client_id": "237115759240-hl7idkucv13gfh0uuejd6e831295snve.apps.googleusercontent.com",
          "client_type": 3
        }
      ],
      "api_key": [
        {
          "current_key": "AIzaSyCJHIlfiEKl_mtlQf0rkmVgA_sJwKJjawg"
        }
      ],
      "services": {
        "appinvite_service": {
          "other_platform_oauth_client": [
            {
              "client_id": "237115759240-hl7idkucv13gfh0uuejd6e831295snve.apps.googleusercontent.com",
              "client_type": 3
            }
          ]
        }
      }
    }
  ],
  "configuration_version": "1"
}